xgrammar/__init__.py
xgrammar/base.py
xgrammar/compiler.py
xgrammar/config.py
xgrammar/contrib/__init__.py
xgrammar/contrib/hf.py
xgrammar/contrib/mlxlm.py
xgrammar/exception.py
xgrammar/grammar.py
xgrammar/include/dlpack/dlpack.h
xgrammar/include/xgrammar/compiler.h
xgrammar/include/xgrammar/config.h
xgrammar/include/xgrammar/exception.h
xgrammar/include/xgrammar/grammar.h
xgrammar/include/xgrammar/matcher.h
xgrammar/include/xgrammar/object.h
xgrammar/include/xgrammar/tokenizer_info.h
xgrammar/include/xgrammar/xgrammar.h
xgrammar/kernels/__init__.py
xgrammar/kernels/apply_token_bitmask_inplace_cpu.py
xgrammar/kernels/apply_token_bitmask_inplace_cuda.cu
xgrammar/kernels/apply_token_bitmask_inplace_cuda.py
xgrammar/kernels/apply_token_bitmask_inplace_torch.py
xgrammar/kernels/apply_token_bitmask_inplace_torch_compile.py
xgrammar/kernels/apply_token_bitmask_inplace_triton.py
xgrammar/kernels/apply_token_bitmask_mlx.py
xgrammar/lib/xgrammar.lib
xgrammar/matcher.py
xgrammar/py.typed
xgrammar/structural_tag.py
xgrammar/support/__init__.py
xgrammar/support/logging.py
xgrammar/testing.py
xgrammar/tokenizer_info.py
xgrammar/xgrammar_bindings.cp314t-win_amd64.pyd
xgrammar-0.1.31.dist-info/METADATA
xgrammar-0.1.31.dist-info/WHEEL
xgrammar-0.1.31.dist-info/licenses/LICENSE
xgrammar-0.1.31.dist-info/licenses/NOTICE
xgrammar-0.1.31.dist-info/RECORD
